C-L/C-L.py
C-L/__init__.py
cl-p/__init__.py
cl-p/a.py
cl-p/logo.py
cl52/__init__.py
cl52/a.py
cl52/logo.py
clp/__init__.py
clp/a.py
clp/logo.py
creeper/__init__.py
creeper/a.py
creeper/logo.py
cyber log/__init__.py
cyber log/a.py
cyber log/logo.py
dot-cyber/__init__.py
dot-cyber/a.py
dot-cyber/logo.py
cl52-1.0.dist-info/LICENSE
cl52-1.0.dist-info/METADATA
cl52-1.0.dist-info/WHEEL
cl52-1.0.dist-info/top_level.txt
cl52-1.0.dist-info/RECORD
