Metadata-Version: 2.1
Name: cl52
Version: 1.0
Summary: This is made for educational purpose
Home-page: UNKNOWN
Author: Al Jabir {Telegram: t.me/jabir52}
Author-email: smaliahsanaljabir@gmail.com
License: UNKNOWN
Platform: UNKNOWN
